{
    "LeftFoot_joint": [
        "accel",
        0.38
    ],
    "LeftLeg_joint": [
        "accel",
        0.2
    ],
    "LFootTongue_joint": [
        "accel",
        0.09
    ],
    "RFootTongue_joint": [
        "accel",
        0.09
    ],
    "RightFoot_joint": [
        "accel",
        0.2
    ],
    "RightLeg_joint": [
        "accel",
        0.38
    ],
    "root_height": [
        "accel",
        0.01
    ],
    "root_location": [
        "accel",
        6.0
    ],
    "root_joint": [
        "accel",
        0.0
    ],
    "tau_weight": 0.0
}